CMakeLists.txt
MANIFEST.in
copy_cores.sh
setup.py
rle_python_interface/__init__.py
rle_python_interface/__init__.pyc
rle_python_interface/librle_c.so
rle_python_interface/rle_c_wrapper.cpp
rle_python_interface/rle_c_wrapper.h
rle_python_interface/rle_python_interface.py
rle_python_interface/rle_python_interface.pyc
rle_python_interface/snes9x2010_libretro.so
rle_python_interface/snes9x2010_libretro1.so
rle_python_interface/snes9x2010_libretro2.so
rle_python_interface.egg-info/PKG-INFO
rle_python_interface.egg-info/SOURCES.txt
rle_python_interface.egg-info/dependency_links.txt
rle_python_interface.egg-info/top_level.txt
src/libretro.h
src/rle_interface.cpp
src/rle_interface.hpp
src/common/Array.hxx
src/common/Constants.cpp
src/common/Constants.h
src/common/DebugMacros.h
src/common/Log.cpp
src/common/Log.hpp
src/common/RleException.h
src/common/ScreenExporter.cpp
src/common/ScreenExporter.hpp
src/common/SoundExporter.cpp
src/common/SoundExporter.hpp
src/common/bspf.hxx
src/common/display_screen.cpp
src/common/display_screen.h
src/common/.deps/SoundSDL.d
src/environment/Deserializer.cxx
src/environment/Deserializer.hxx
src/environment/FSNode.cxx
src/environment/FSNode.hxx
src/environment/Random.cxx
src/environment/Random.hxx
src/environment/RetroAgent.cpp
src/environment/RetroAgent.h
src/environment/RleSystem.cxx
src/environment/RleSystem.hxx
src/environment/Serializer.cxx
src/environment/Serializer.hxx
src/environment/Settings.cxx
src/environment/Settings.hxx
src/environment/phosphor_blend.cpp
src/environment/phosphor_blend.hpp
src/environment/retro_environment.cpp
src/environment/retro_environment.hpp
src/environment/rle_ram.cpp
src/environment/rle_screen.cpp
src/environment/rle_state.cpp
src/environment/rle_state.hpp
src/external/TinyMT/LICENSE.txt
src/external/TinyMT/tinymt32.c
src/external/TinyMT/tinymt32.h
src/external/TinyMT/.deps/tinymt32.d
src/games/AtariSettings.cpp
src/games/AtariSettings.hpp
src/games/GenesisSettings.cpp
src/games/GenesisSettings.hpp
src/games/RomSettings.cpp
src/games/RomSettings.hpp
src/games/RomUtils.cpp
src/games/RomUtils.hpp
src/games/Roms.cpp
src/games/Roms.hpp
src/games/SnesSettings.cpp
