Metadata-Version: 1.1
Name: rle-python-interface
Version: 1.1.5
Summary: Retro Learning Environment Python Interface based on Ben Goodrich's work
Home-page: https://github.com/nadavbh12/Retro-Learning-Environment
Author: Nadav Bhonker, Shai Rozenberg
Author-email: nadavbh@gmail.com;shai.roz1989@gmail.com
License: GPL
Download-URL: https://github.com/nadavbh12/Retro-Learning-Environment/tarball/1.1.5
Platform: UNKNOWN
